<?xml version="1.0" encoding="UTF-8"?>
<configuration>
    <logfile>E:\heimdall\logfile.log</logfile>
    <command_jail>/sbin/ip{version}tables -I INPUT 1 -s {ip} -j DROP</command_jail>
    <command_unjail>/sbin/ip{version}tables -D INPUT -s {ip} -j DROP</command_unjail>
    <observers jail_time="1200">

        <observer name="ssh" limit_count="2" limit_minutes="10">
            <file>E:\heimdall\logfiles\ssh.txt</file>
            <patterns>
                <pattern>{hh:mm:ss}.*Failed password.*from {ip}</pattern>
                <pattern>{hh:mm:ss}.*2 more authentication failures.*rhost={ip}</pattern>
            </patterns>
        </observer>

        <!--
        <observer name="apache" limit_count="10" limit_minutes="2">
            <file>E:\heimdall\logfiles\access_log</file>
            <patterns>
                <pattern>{ip}.*\[[^\]]*{hh:mm:ss}[^\]]*\] "POST /wp-login.php</pattern>
                <pattern>{ip}.*\[[^\]]*{hh:mm:ss}[^\]]*\] "GET /phpmyadmin/scripts/setup.php</pattern>
                <pattern>{ip}.*\[[^\]]*{hh:mm:ss}[^\]]*\] "POST //?xmlrpc.php</pattern>
            </patterns>
        </observer>

        <observer name="mail" limit_count="7" limit_minutes="1">
            <file>/var/log/maillog</file>
            <patterns>
                <pattern>{hh:mm:ss}.*\[{ip}\]: SASL LOGIN authentication failed</pattern>
            </patterns>
        </observer>
        -->

    </observers>
</configuration>
